zc_common/__init__.py
zc_common/databaseless_test_runner.py
zc_common/fields.py
zc_common/settings.py
zc_common/timezone.py
zc_common/views.py
zc_common/jwt_auth/__init__.py
zc_common/jwt_auth/authentication.py
zc_common/jwt_auth/permissions.py
zc_common/jwt_auth/tests.py
zc_common/jwt_auth/utils.py
zc_common/monitoring/__init__.py
zc_common/monitoring/statsd_client.py
zc_common/remote_resource/__init__.py
zc_common/remote_resource/filters.py
zc_common/remote_resource/metadata.py
zc_common/remote_resource/models.py
zc_common/remote_resource/negotiation.py
zc_common/remote_resource/pagination.py
zc_common/remote_resource/parsers.py
zc_common/remote_resource/relations.py
zc_common/remote_resource/renderers.py
zc_common/remote_resource/serializers.py
zc_common/remote_resource/test_mixins.py
zc_common/remote_resource/tests.py
zc_common/remote_resource/utils.py
zc_common/remote_resource/views.py
zc_common-0.4.17.dist-info/DESCRIPTION.rst
zc_common-0.4.17.dist-info/METADATA
zc_common-0.4.17.dist-info/RECORD
zc_common-0.4.17.dist-info/WHEEL
zc_common-0.4.17.dist-info/metadata.json
zc_common-0.4.17.dist-info/top_level.txt
