Metadata-Version: 2.0
Name: zc-common
Version: 0.4.17
Summary: Shared code for ZeroCater microservices
Home-page: https://github.com/ZeroCater/zc_common
Author: ZeroCater
Author-email: tech@zerocater.com
License: MIT
Download-URL: https://github.com/ZeroCater/zc_common/tarball/0.4.17
Keywords: zerocater python util
Platform: UNKNOWN
Classifier: License :: OSI Approved :: MIT License
Classifier: Programming Language :: Python
Classifier: Development Status :: 5 - Production/Stable
Classifier: Intended Audience :: Developers
Classifier: Topic :: Internet :: WWW/HTTP
Requires-Dist: python-dateutil (>=2.6.1)
Requires-Dist: ujson (<1.36,>=1.35)
Requires-Dist: PyJWT (>=1.6.4)
Requires-Dist: inflection (>=0.3.1)
Requires-Dist: pytz (>=2014.2)
Requires-Dist: python-dateutil (>=2.7.3)
